{
  "Football": [
    {
      "id": "9943",
      "name": "Senegal at France (English)",
      "url": "https://edgestreams.pro/hls/24SDAZFcsqnj24.m3u8?st=s03ckmQeo7feOPXlLPs1ZyLn0_Dn7oh-SqGgDYn69TY&e=1781658888",
      "start": "2026-06-16T20:00:00",
      "categoryId": 9,
      "logo": "https://a.espncdn.com/i/teamlogos/countries/500/fra.png"
    },
    {
      "id": "9943",
      "name": "Senegal at France (Spanish)",
      "url": "https://edge2caster.pro/hls/eJmauBDCIf.m3u8?st=JOLrFdWb-sO1CRUtW5AuZtxuyCFIFHedAGrHQU3qMgs&e=1781658888",
      "start": "2026-06-16T20:00:00",
      "categoryId": 9,
      "logo": "https://a.espncdn.com/i/teamlogos/countries/500/fra.png"
    },
    {
      "id": "9943",
      "name": "Senegal at France (English)",
      "url": "https://edgestreams.pro/hls/b0h5fNwDKH.m3u8?st=6w-FYlTsn3V_F3fBVst4RVQWC0h1tDjHbPXGBwiLRLM&e=1781658888",
      "start": "2026-06-16T20:00:00",
      "categoryId": 9,
      "logo": "https://a.espncdn.com/i/teamlogos/countries/500/fra.png"
    },
    {
      "id": "9943",
      "name": "Senegal at France (Arabic)",
      "url": "https://edgestreams.pro/hls/sqdahach1ax.m3u8?st=iRlOjOeDLJV9lKZZhO01_nT7yJQhB-azrBrBRRe36s4&e=1781658888",
      "start": "2026-06-16T20:00:00",
      "categoryId": 9,
      "logo": "https://a.espncdn.com/i/teamlogos/countries/500/fra.png"
    },
    {
      "id": "9943",
      "name": "Senegal at France (French)",
      "url": "https://edgestreams.pro/hls/griogoehvn2.m3u8?st=XrshlS1qMZYJAlBJaxL5XKKdZK0LTB3mKeS7dCqlfUc&e=1781658888",
      "start": "2026-06-16T20:00:00",
      "categoryId": 9,
      "logo": "https://a.espncdn.com/i/teamlogos/countries/500/fra.png"
    },
    {
      "id": "9944",
      "name": "Norway at Iraq (English)",
      "url": "https://edge2caster.pro/hls/24SDAZFcsqnj24.m3u8?st=gIKdDkg9FJvUQYGrcr_ZYhsG03uV-E3GLu-4PMlBLyw&e=1781658887",
      "start": "2026-06-16T23:00:00",
      "categoryId": 9,
      "logo": "https://a.espncdn.com/i/teamlogos/countries/500/irq.png"
    },
    {
      "id": "9944",
      "name": "Norway at Iraq (Spanish)",
      "url": "https://edgestreams.pro/hls/eJmauBDCIf.m3u8?st=QaV8ERlJQps7wsouzRbfdcdM9C17bw9smynVRIg9N5E&e=1781658887",
      "start": "2026-06-16T23:00:00",
      "categoryId": 9,
      "logo": "https://a.espncdn.com/i/teamlogos/countries/500/irq.png"
    },
    {
      "id": "9944",
      "name": "Norway at Iraq (English)",
      "url": "https://edgestreams.pro/hls/b0h5fNwDKH.m3u8?st=Aqft1Fqx8FDY6liGGipLoL7CNUHCwyIe3-JpMfp5g4Q&e=1781658887",
      "start": "2026-06-16T23:00:00",
      "categoryId": 9,
      "logo": "https://a.espncdn.com/i/teamlogos/countries/500/irq.png"
    },
    {
      "id": "9944",
      "name": "Norway at Iraq (Arabic)",
      "url": "https://edge2caster.pro/hls/sqdahach1ax.m3u8?st=YqD37crg2KFDKgZJ2G6b2_zmED2yiD8bltn4Hp9t9Vg&e=1781658887",
      "start": "2026-06-16T23:00:00",
      "categoryId": 9,
      "logo": "https://a.espncdn.com/i/teamlogos/countries/500/irq.png"
    },
    {
      "id": "9945",
      "name": "Algeria at Argentina (English)",
      "url": "https://edge2caster.pro/hls/24SDAZFcsqnj24.m3u8?st=JM30agDZS2q1vjzv-H-jpS-ejPUDsnCm3FubVJ5FR9c&e=1781658885",
      "start": "2026-06-17T02:00:00",
      "categoryId": 9,
      "logo": "https://a.espncdn.com/i/teamlogos/countries/500/arg.png"
    },
    {
      "id": "9945",
      "name": "Algeria at Argentina (Spanish)",
      "url": "https://edgestreams.pro/hls/eJmauBDCIf.m3u8?st=In3MZzq6DTjImOzljYyCSXS5tmRpBdpIOFIDE1JIQUc&e=1781658885",
      "start": "2026-06-17T02:00:00",
      "categoryId": 9,
      "logo": "https://a.espncdn.com/i/teamlogos/countries/500/arg.png"
    },
    {
      "id": "9945",
      "name": "Algeria at Argentina (English)",
      "url": "https://edgestreams.pro/hls/b0h5fNwDKH.m3u8?st=BIZO02LjsXbxIIr6FSb0-pF8gupmhMB19JIkq8HKd-Q&e=1781658885",
      "start": "2026-06-17T02:00:00",
      "categoryId": 9,
      "logo": "https://a.espncdn.com/i/teamlogos/countries/500/arg.png"
    },
    {
      "id": "9945",
      "name": "Algeria at Argentina (Arabic)",
      "url": "https://edge2caster.pro/hls/sqdahach1ax.m3u8?st=9aTG9PfkD5uxA9W71VUhDU_EmP4MwV53PmtJvf-GrdA&e=1781658885",
      "start": "2026-06-17T02:00:00",
      "categoryId": 9,
      "logo": "https://a.espncdn.com/i/teamlogos/countries/500/arg.png"
    },
    {
      "id": "9946",
      "name": "Jordan at Austria (English)",
      "url": "https://edgestreams.pro/hls/24SDAZFcsqnj24.m3u8?st=G3o9FmpcHhpEyHXuhG1qsrOe7iInqOJpmFxrNi30FwU&e=1781658883",
      "start": "2026-06-17T05:00:00",
      "categoryId": 9,
      "logo": "https://a.espncdn.com/i/teamlogos/countries/500/aut.png"
    },
    {
      "id": "9946",
      "name": "Jordan at Austria (Spanish)",
      "url": "https://edge2caster.pro/hls/eJmauBDCIf.m3u8?st=1kyfyEVgbhI4rWs2VntulY7lcMFuRjkI3vHzbL31p4s&e=1781658883",
      "start": "2026-06-17T05:00:00",
      "categoryId": 9,
      "logo": "https://a.espncdn.com/i/teamlogos/countries/500/aut.png"
    },
    {
      "id": "9946",
      "name": "Jordan at Austria (English)",
      "url": "https://edge2caster.pro/hls/b0h5fNwDKH.m3u8?st=NET57kMktlWoLqrC9rLVE-KHPaBYRbF4yOusB1RTUyY&e=1781658883",
      "start": "2026-06-17T05:00:00",
      "categoryId": 9,
      "logo": "https://a.espncdn.com/i/teamlogos/countries/500/aut.png"
    },
    {
      "id": "9946",
      "name": "Jordan at Austria (Arabic)",
      "url": "https://edge2caster.pro/hls/sqdahach1ax.m3u8?st=GqwWkBQvTpSTJtGqc5oY00f5ftyDQLjXUVWKLOZWb2g&e=1781658883",
      "start": "2026-06-17T05:00:00",
      "categoryId": 9,
      "logo": "https://a.espncdn.com/i/teamlogos/countries/500/aut.png"
    }
  ],
  "Other": [
    {
      "id": "9947",
      "name": "Miami Marlins at Philadelphia Phillies (English)",
      "url": "https://edge2caster.pro/hls/dazhfiach15.m3u8?st=SIPXt9u4CdbJ5dSAuwys2UVBNlfqcT-aSLDfuARgHJ8&e=1781658887",
      "start": "2026-06-16T23:40:00",
      "categoryId": 13,
      "logo": "https://a.espncdn.com/i/teamlogos/mlb/500/scoreboard/phi.png"
    },
    {
      "id": "9948",
      "name": "Kansas City Royals at Washington Nationals (English)",
      "url": "https://edge2caster.pro/hls/16yuitzaerghbhc16.m3u8?st=DAsLI-vtjK7MFlQD8Fw3Y9OyVikYIcJsUr6rZt_4kTg&e=1781658887",
      "start": "2026-06-16T23:45:00",
      "categoryId": 13,
      "logo": "https://a.espncdn.com/i/teamlogos/mlb/500/scoreboard/wsh.png"
    },
    {
      "id": "9949",
      "name": "Toronto Blue Jays at Boston Red Sox (English)",
      "url": "https://edgestreams.pro/hls/ihfazugfyjcazich17.m3u8?st=wW7FXouF3aZH46V7WsFds5RoJOz2ID9KJSDI0XlpDus&e=1781658887",
      "start": "2026-06-16T23:45:00",
      "categoryId": 13,
      "logo": "https://a.espncdn.com/i/teamlogos/mlb/500/scoreboard/bos.png"
    },
    {
      "id": "9962",
      "name": "Toronto Tempo at Indiana Fever (English)",
      "url": "https://edge2caster.pro/hls/bvnsqdfvgha70.m3u8?st=scNroDJCcIy5jwXGA22FKpQYAD86lbKitAgfDDAxjOU&e=1781658887",
      "start": "2026-06-17T00:00:00",
      "categoryId": 4,
      "logo": "https://a.espncdn.com/i/teamlogos/wnba/500/ind.png"
    },
    {
      "id": "9950",
      "name": "Chicago White Sox at New York Yankees (English)",
      "url": "https://edgestreams.pro/hls/Czajafjihafch18.m3u8?st=jS7mwRJX2Cs5HrenOoHPekyV_jEWlviz24iQEJgPjsw&e=1781658886",
      "start": "2026-06-17T00:05:00",
      "categoryId": 13,
      "logo": "https://a.espncdn.com/i/teamlogos/mlb/500/scoreboard/nyy.png"
    },
    {
      "id": "9951",
      "name": "New York Mets at Cincinnati Reds (English)",
      "url": "https://edgestreams.pro/hls/bzagLHzach19.m3u8?st=jF32CVMWr2fhTxSmXCUkVjhdo1Ctb0lCuMnXNxytITY&e=1781658886",
      "start": "2026-06-17T00:10:00",
      "categoryId": 13,
      "logo": "https://a.espncdn.com/i/teamlogos/mlb/500/scoreboard/cin.png"
    },
    {
      "id": "9952",
      "name": "San Francisco Giants at Atlanta Braves (English)",
      "url": "https://edgestreams.pro/hls/jkzahzadach20.m3u8?st=XORRrSXOdJqb2mYNMybN39XLdzu1l_DDsoTIKjuclcI&e=1781658886",
      "start": "2026-06-17T00:15:00",
      "categoryId": 13,
      "logo": "https://a.espncdn.com/i/teamlogos/mlb/500/scoreboard/atl.png"
    },
    {
      "id": "9953",
      "name": "Cleveland Guardians at Milwaukee Brewers (English)",
      "url": "https://edgestreams.pro/hls/ojzkajnach21.m3u8?st=YcjExdjCYsLzbpuRgTWzpB5peRFEFXWpx-yy8_xM90U&e=1781658886",
      "start": "2026-06-17T00:40:00",
      "categoryId": 13,
      "logo": "https://a.espncdn.com/i/teamlogos/mlb/500/scoreboard/mil.png"
    },
    {
      "id": "9954",
      "name": "San Diego Padres at St. Louis Cardinals (English)",
      "url": "https://edgestreams.pro/hls/ijfnakfidch22.m3u8?st=A4CBlrg0rdASt9hXQ4h-SuiXFL5lQTUiHVNWz025JXw&e=1781658886",
      "start": "2026-06-17T00:45:00",
      "categoryId": 13,
      "logo": "https://a.espncdn.com/i/teamlogos/mlb/500/scoreboard/stl.png"
    },
    {
      "id": "9955",
      "name": "Colorado Rockies at Chicago Cubs (English)",
      "url": "https://edge2caster.pro/hls/jnzkdzjfanch23.m3u8?st=B0mns-ca1CB_ygH3ToicjLJANRYh6nfEaRMirhzaYyI&e=1781658886",
      "start": "2026-06-17T01:05:00",
      "categoryId": 13,
      "logo": "https://a.espncdn.com/i/teamlogos/mlb/500/scoreboard/chc.png"
    },
    {
      "id": "9956",
      "name": "Minnesota Twins at Texas Rangers (English)",
      "url": "https://edge2caster.pro/hls/fskjanach24.m3u8?st=_mGpwS4KrxdZHJYKFmJmKK8zMQfNTyOxIy2t3WZDD3g&e=1781658886",
      "start": "2026-06-17T01:05:00",
      "categoryId": 13,
      "logo": "https://a.espncdn.com/i/teamlogos/mlb/500/scoreboard/tex.png"
    },
    {
      "id": "9957",
      "name": "Detroit Tigers at Houston Astros (English)",
      "url": "https://edgestreams.pro/hls/kjhfzua25.m3u8?st=EBmrK966V0x84MjLoMCRFVDw9pgXVoyU4e9qRUB3Gm8&e=1781658885",
      "start": "2026-06-17T01:10:00",
      "categoryId": 13,
      "logo": "https://a.espncdn.com/i/teamlogos/mlb/500/scoreboard/hou.png"
    },
    {
      "id": "9958",
      "name": "Los Angeles Angels at Arizona Diamondbacks (English)",
      "url": "https://edgestreams.pro/hls/dzjhkfazbka26.m3u8?st=MDAJoHkZeipAdRdfyAHW1_Of-6b_eE00v2b1dBLxNtU&e=1781658884",
      "start": "2026-06-17T02:40:00",
      "categoryId": 13,
      "logo": "https://a.espncdn.com/i/teamlogos/mlb/500/scoreboard/ari.png"
    },
    {
      "id": "9959",
      "name": "Baltimore Orioles at Seattle Mariners (English)",
      "url": "https://edgestreams.pro/hls/jzabfazkbf27.m3u8?st=rXjjxI7IQhXh85Ohe5zHrZTpyUdnhIvaHuYJWgnEW8k&e=1781658884",
      "start": "2026-06-17T02:40:00",
      "categoryId": 13,
      "logo": "https://a.espncdn.com/i/teamlogos/mlb/500/scoreboard/sea.png"
    },
    {
      "id": "9960",
      "name": "Pittsburgh Pirates at Athletics Athletics (English)",
      "url": "https://edgestreams.pro/hls/hefbafbakx28.m3u8?st=MPe9B1saBBpkYgXTvDFsVy64aNPHs-0paBmS9rvSCSg&e=1781658884",
      "start": "2026-06-17T02:40:00",
      "categoryId": 13,
      "logo": "https://a.espncdn.com/i/teamlogos/mlb/500/scoreboard/ath.png"
    },
    {
      "id": "9961",
      "name": "Tampa Bay Rays at Los Angeles Dodgers (English)",
      "url": "https://edgestreams.pro/hls/hfzljfahzcax29.m3u8?st=l9gys4mDfgRwmYkh71Lgm1NN3MxuYKUWJHqrURmks90&e=1781658884",
      "start": "2026-06-17T03:10:00",
      "categoryId": 13,
      "logo": "https://a.espncdn.com/i/teamlogos/mlb/500/scoreboard/lad.png"
    }
  ]
}