{
  "Other": [
    {
      "id": "10420",
      "name": "Toronto Blue Jays at San Francisco Giants (English)",
      "url": "https://edgestream2.pro/hls/dazhfiach15.m3u8?st=zsCxRluzm0HX6T4Daoye4iIvddndJuA-DPl7DNcIVRg&e=1783545599",
      "start": "2026-07-08T20:45:00",
      "categoryId": 13,
      "logo": "https://a.espncdn.com/i/teamlogos/mlb/500/scoreboard/sf.png"
    },
    {
      "id": "10421",
      "name": "Chicago Cubs at Baltimore Orioles (English)",
      "url": "https://edgestream3.pro/hls/16yuitzaerghbhc16.m3u8?st=O2IrtvV1Yxe5pOVdQs7k7Vn01ppxuVptwb931g2okDk&e=1783545599",
      "start": "2026-07-08T23:35:00",
      "categoryId": 13,
      "logo": "https://a.espncdn.com/i/teamlogos/mlb/500/scoreboard/bal.png"
    },
    {
      "id": "10422",
      "name": "Athletics Athletics at Detroit Tigers (English)",
      "url": "https://edgestream1.pro/hls/ihfazugfyjcazich17.m3u8?st=O3B-EHMCfM6TvwmFkQKi_Y1uhUee49aFfrMQtwHnP-g&e=1783545599",
      "start": "2026-07-08T23:40:00",
      "categoryId": 13,
      "logo": "https://a.espncdn.com/i/teamlogos/mlb/500/scoreboard/det.png"
    },
    {
      "id": "10423",
      "name": "Atlanta Braves at Pittsburgh Pirates (English)",
      "url": "https://edgestream1.pro/hls/Czajafjihafch18.m3u8?st=k-fa4072uxNfA_XoC_7U5Y1bpk2E9mb_7DSr6TpOr44&e=1783545599",
      "start": "2026-07-08T23:40:00",
      "categoryId": 13,
      "logo": "https://a.espncdn.com/i/teamlogos/mlb/500/scoreboard/pit.png"
    },
    {
      "id": "10424",
      "name": "New York Yankees at Tampa Bay Rays (English)",
      "url": "https://edgestream3.pro/hls/bzagLHzach19.m3u8?st=Fm1oJJpV_SXe1-HRHk7Y7S_NSEPlacBW_EDXBsNgnVA&e=1783545599",
      "start": "2026-07-08T23:40:00",
      "categoryId": 13,
      "logo": "https://a.espncdn.com/i/teamlogos/mlb/500/scoreboard/tb.png"
    },
    {
      "id": "10425",
      "name": "Seattle Mariners at Miami Marlins (English)",
      "url": "https://edgestream1.pro/hls/jkzahzadach20.m3u8?st=ex2_zLF4_gep-RBFqqbavC3WvTGx_wvUFRP2uUUxUpg&e=1783545599",
      "start": "2026-07-08T23:40:00",
      "categoryId": 13,
      "logo": "https://a.espncdn.com/i/teamlogos/mlb/500/scoreboard/mia.png"
    },
    {
      "id": "10426",
      "name": "Houston Astros at Washington Nationals (English)",
      "url": "https://edgestream2.pro/hls/ojzkajnach21.m3u8?st=ZSF4TFlJ55MdLy7qV2-9eJwwX9XzvTcOiE-A6P6wxWU&e=1783545599",
      "start": "2026-07-08T23:45:00",
      "categoryId": 13,
      "logo": "https://a.espncdn.com/i/teamlogos/mlb/500/scoreboard/wsh.png"
    },
    {
      "id": "10435",
      "name": "Golden State Valkyries at Toronto Tempo (English)",
      "url": "https://edgestream2.pro/hls/bvnsqdfvgha70.m3u8?st=dksFf__R7lXx5R_Os9-p1HCZJKtmHioO9yf7iOPhYqU&e=1783545599",
      "start": "2026-07-09T00:00:00",
      "categoryId": 4,
      "logo": "https://a.espncdn.com/i/teamlogos/wnba/500/tor.png"
    },
    {
      "id": "10427",
      "name": "Philadelphia Phillies at Cincinnati Reds (English)",
      "url": "https://edgestream3.pro/hls/ijfnakfidch22.m3u8?st=6pLTYY-srB3CTstTW2YpEXXGPDySXLb1tr1JhqTdRgw&e=1783545599",
      "start": "2026-07-09T00:00:00",
      "categoryId": 13,
      "logo": "https://a.espncdn.com/i/teamlogos/mlb/500/scoreboard/cin.png"
    },
    {
      "id": "10428",
      "name": "Kansas City Royals at New York Mets (English)",
      "url": "https://edgestream1.pro/hls/jnzkdzjfanch23.m3u8?st=cLb_V7ZRJVuPT4tfotBu_X-k-vDmogOb2wbjGL9ba2U&e=1783545599",
      "start": "2026-07-09T00:10:00",
      "categoryId": 13,
      "logo": "https://a.espncdn.com/i/teamlogos/mlb/500/scoreboard/nym.png"
    },
    {
      "id": "10436",
      "name": "Minnesota Lynx at Connecticut Sun (English)",
      "url": "https://edgestream3.pro/hls/ztyarueaghj71.m3u8?st=tesUmzQ8GjLfpJ0yBtrSydr5olVBBGKu1hFg2RNGyh8&e=1783545598",
      "start": "2026-07-09T00:30:00",
      "categoryId": 4,
      "logo": "https://a.espncdn.com/i/teamlogos/wnba/500/con.png"
    },
    {
      "id": "10429",
      "name": "Boston Red Sox at Chicago White Sox (English)",
      "url": "https://edgestream3.pro/hls/fskjanach24.m3u8?st=ZaL-37n1_wMAdHCLmQWHpxpoA2lWH_G9eC_q1O2fh4Y&e=1783545598",
      "start": "2026-07-09T00:40:00",
      "categoryId": 13,
      "logo": "https://a.espncdn.com/i/teamlogos/mlb/500/scoreboard/chw.png"
    },
    {
      "id": "10430",
      "name": "Cleveland Guardians at Minnesota Twins (English)",
      "url": "https://edgestream3.pro/hls/kjhfzua25.m3u8?st=O0zdFuNWAFqzEGIPNDXU-2rvrzlwvwaCtuHnxS8VCYU&e=1783545598",
      "start": "2026-07-09T00:40:00",
      "categoryId": 13,
      "logo": "https://a.espncdn.com/i/teamlogos/mlb/500/scoreboard/min.png"
    },
    {
      "id": "10431",
      "name": "Milwaukee Brewers at St. Louis Cardinals (English)",
      "url": "https://edgestream2.pro/hls/dzjhkfazbka26.m3u8?st=-IH5yfjf_tOehFME-4vL-1Hri18FcqiIzAwR6LD8KXA&e=1783545598",
      "start": "2026-07-09T00:45:00",
      "categoryId": 13,
      "logo": "https://a.espncdn.com/i/teamlogos/mlb/500/scoreboard/stl.png"
    },
    {
      "id": "10432",
      "name": "Los Angeles Angels at Texas Rangers (English)",
      "url": "https://edgestream3.pro/hls/jzabfazkbf27.m3u8?st=9FZQ-jaGChrHVxB1KFHzYGAzcW203KLKOoGhOCGo7dk&e=1783545598",
      "start": "2026-07-09T01:05:00",
      "categoryId": 13,
      "logo": "https://a.espncdn.com/i/teamlogos/mlb/500/scoreboard/tex.png"
    },
    {
      "id": "10433",
      "name": "Arizona Diamondbacks at San Diego Padres (English)",
      "url": "https://edgestream2.pro/hls/hefbafbakx28.m3u8?st=qRSpyQ2afXklNJPA2WbBMk3u2crKz7_5Q_PK63-DNNc&e=1783545598",
      "start": "2026-07-09T03:00:00",
      "categoryId": 13,
      "logo": "https://a.espncdn.com/i/teamlogos/mlb/500/scoreboard/sd.png"
    },
    {
      "id": "10437",
      "name": "Indiana Fever at Los Angeles Sparks (English)",
      "url": "https://edgestream3.pro/hls/pllmazjkdzajh72.m3u8?st=14WaDA7WewyqwMEut-I-LED0FjPcYKig9UhzLbwGIPM&e=1783545598",
      "start": "2026-07-09T03:00:00",
      "categoryId": 4,
      "logo": "https://a.espncdn.com/i/teamlogos/wnba/500/la.png"
    },
    {
      "id": "10434",
      "name": "Colorado Rockies at Los Angeles Dodgers (English)",
      "url": "https://edgestream1.pro/hls/hfzljfahzcax29.m3u8?st=WSaJ__v2xhDnzdlJFrOE8vxb3rryl9awfXaOw_w6yNE&e=1783545598",
      "start": "2026-07-09T03:10:00",
      "categoryId": 13,
      "logo": "https://a.espncdn.com/i/teamlogos/mlb/500/scoreboard/lad.png"
    }
  ]
}