<?xml version="1.0" ?>
<tv>
  <channel id="9703">
    <display-name>Motogp HUNGARY (English)</display-name>
    <icon src=""/>
  </channel>
  <programme start="20260606045521 +0000" stop="20260606105521 +0000" channel="9703">
    <title lang="en">Motogp HUNGARY (English)</title>
    <icon src=""/>
  </programme>
  <channel id="9716">
    <display-name>New York Mets at San Diego Padres (English)</display-name>
    <icon src=""/>
  </channel>
  <programme start="20260606045521 +0000" stop="20260606105521 +0000" channel="9716">
    <title lang="en">New York Mets at San Diego Padres (English)</title>
    <icon src=""/>
  </programme>
  <channel id="9717">
    <display-name>Washington Nationals at Arizona Diamondbacks (English)</display-name>
    <icon src=""/>
  </channel>
  <programme start="20260606045521 +0000" stop="20260606105521 +0000" channel="9717">
    <title lang="en">Washington Nationals at Arizona Diamondbacks (English)</title>
    <icon src=""/>
  </programme>
  <channel id="9725">
    <display-name>Dallas Wings at Los Angeles Sparks (English)</display-name>
    <icon src=""/>
  </channel>
  <programme start="20260606045521 +0000" stop="20260606105521 +0000" channel="9725">
    <title lang="en">Dallas Wings at Los Angeles Sparks (English)</title>
    <icon src=""/>
  </programme>
  <channel id="9726">
    <display-name>Phoenix Mercury at Portland Fire (English)</display-name>
    <icon src=""/>
  </channel>
  <programme start="20260606045521 +0000" stop="20260606105521 +0000" channel="9726">
    <title lang="en">Phoenix Mercury at Portland Fire (English)</title>
    <icon src=""/>
  </programme>
  <channel id="9718">
    <display-name>Los Angeles Angels at Los Angeles Dodgers (English)</display-name>
    <icon src=""/>
  </channel>
  <programme start="20260606045521 +0000" stop="20260606105521 +0000" channel="9718">
    <title lang="en">Los Angeles Angels at Los Angeles Dodgers (English)</title>
    <icon src=""/>
  </programme>
  <channel id="9700">
    <display-name>Monaco Grand Prix  Practice 3 (English)</display-name>
    <icon src=""/>
  </channel>
  <programme start="20260606045521 +0000" stop="20260606105521 +0000" channel="9700">
    <title lang="en">Monaco Grand Prix  Practice 3 (English)</title>
    <icon src=""/>
  </programme>
  <channel id="9727">
    <display-name>Tunisia at Belgium (English)</display-name>
    <icon src=""/>
  </channel>
  <programme start="20260606045521 +0000" stop="20260606105521 +0000" channel="9727">
    <title lang="en">Tunisia at Belgium (English)</title>
    <icon src=""/>
  </programme>
  <channel id="9701">
    <display-name>Monaco Grand Prix Qualifying (English)</display-name>
    <icon src=""/>
  </channel>
  <programme start="20260606045521 +0000" stop="20260606105521 +0000" channel="9701">
    <title lang="en">Monaco Grand Prix Qualifying (English)</title>
    <icon src=""/>
  </programme>
  <channel id="9729">
    <display-name>Chile at Portugal (English)</display-name>
    <icon src=""/>
  </channel>
  <programme start="20260606045521 +0000" stop="20260606105521 +0000" channel="9729">
    <title lang="en">Chile at Portugal (English)</title>
    <icon src=""/>
  </programme>
  <channel id="9728">
    <display-name>Germany at United States (English)</display-name>
    <icon src=""/>
  </channel>
  <programme start="20260606045521 +0000" stop="20260606105521 +0000" channel="9728">
    <title lang="en">Germany at United States (English)</title>
    <icon src=""/>
  </programme>
  <channel id="9730">
    <display-name>Australia at Switzerland (English)</display-name>
    <icon src=""/>
  </channel>
  <programme start="20260606045521 +0000" stop="20260606105521 +0000" channel="9730">
    <title lang="en">Australia at Switzerland (English)</title>
    <icon src=""/>
  </programme>
  <channel id="9731">
    <display-name>New Zealand at England (English)</display-name>
    <icon src=""/>
  </channel>
  <programme start="20260606045521 +0000" stop="20260606105521 +0000" channel="9731">
    <title lang="en">New Zealand at England (English)</title>
    <icon src=""/>
  </programme>
  <channel id="9732">
    <display-name>Egypt at Brazil (Spanish)</display-name>
    <icon src=""/>
  </channel>
  <programme start="20260606045521 +0000" stop="20260606105521 +0000" channel="9732">
    <title lang="en">Egypt at Brazil (Spanish)</title>
    <icon src=""/>
  </programme>
  <channel id="9702">
    <display-name>Monaco Grand Prix Race (English)</display-name>
    <icon src=""/>
  </channel>
  <programme start="20260606045521 +0000" stop="20260606105521 +0000" channel="9702">
    <title lang="en">Monaco Grand Prix Race (English)</title>
    <icon src=""/>
  </programme>
</tv>
